nanoscopy/__init__.py
nanoscopy/utilities.py
nanoscopy/afm/AFMForceRecovery.py
nanoscopy/afm/__init__.py
nanoscopy/loaders/__init__.py
nanoscopy/loaders/dataIO.py
nanoscopy/plot/PlotGen - Backup.py
nanoscopy/plot/__init__.py
nanoscopy/plot/plot_gen.py
nanoscopy/plot/plot_styles.py
nanoscopy/spectrum/__init__.py
nanoscopy/spectrum/analysis.py
nanoscopy/spectrum/io.py
nanoscopy/spectrum/peak_fit.py
nanoscopy/spectrum/spectrum.py
nanoscopy/spm/SPMImage.py
nanoscopy/spm/__init__.py
nanoscopy/spm/analysis.py
nanoscopy/spm/driftspeed.py
nanoscopy/spm/io.py
nanoscopy/spm/process.py
NanoscoPy-0.0.13.dist-info/LICENSE
NanoscoPy-0.0.13.dist-info/METADATA
NanoscoPy-0.0.13.dist-info/WHEEL
NanoscoPy-0.0.13.dist-info/top_level.txt
NanoscoPy-0.0.13.dist-info/RECORD
