Metadata-Version: 2.1
Name: NanoscoPy
Version: 0.0.13
Summary: microscopy data processor
Home-page: https://github.com/darianSmalley/NanoscoPy
Author: Jesse Thompson, Darian Smalley
Author-email: darian.smalley@gmail.com
License: UNKNOWN
Project-URL: Bug Tracker, https://github.com/darianSmalley/NanoscoPy/issues
Platform: UNKNOWN
Classifier: Programming Language :: Python :: 3
Classifier: Operating System :: OS Independent
Classifier: License :: OSI Approved :: MIT License
Requires-Python: >=3.6
License-File: LICENSE
